{
  "name": "MatrixMultiply",
  "type": "MatrixMultiply",
  "library": "orodruin-library",
  "ports": [
    {
      "name": "input1",
      "direction": "input",
      "type": "Matrix4",
      "value": [ 1.0, 0.0, 0.0, 0.0, 0.0, 1.0, 0.0, 0.0, 0.0, 0.0, 1.0, 0.0, 0.0, 0.0, 0.0, 1.0 ]
    },
    {
      "name": "input2",
      "direction": "input",
      "type": "Matrix4",
      "value": [ 1.0, 0.0, 0.0, 0.0, 0.0, 1.0, 0.0, 0.0, 0.0, 0.0, 1.0, 0.0, 0.0, 0.0, 0.0, 1.0 ]
    },
    {
      "name": "output",
      "direction": "output",
      "type": "Matrix4",
      "value": [ 1.0, 0.0, 0.0, 0.0, 0.0, 1.0, 0.0, 0.0, 0.0, 0.0, 1.0, 0.0, 0.0, 0.0, 0.0, 1.0 ]
    } ],
  "graph": {
    "nodes": [],
    "connections": []
  }
}